pytest_libiio/__init__.py
pytest_libiio/coverage.py
pytest_libiio/meta.py
pytest_libiio/mkpatch.py
pytest_libiio/plugin.py
pytest_libiio/tools.py
pytest_libiio/resources/adi_hardware_map.yml
pytest_libiio/resources/devices/ad4020.xml
pytest_libiio/resources/devices/ad9081.xml
pytest_libiio/resources/devices/ad9081_tdd.xml
pytest_libiio/resources/devices/ad9172.xml
pytest_libiio/resources/devices/ad9265.xml
pytest_libiio/resources/devices/ad9371.xml
pytest_libiio/resources/devices/ad9375.xml
pytest_libiio/resources/devices/ad9434.xml
pytest_libiio/resources/devices/adrv9002.xml
pytest_libiio/resources/devices/adrv9002_singledma.xml
pytest_libiio/resources/devices/adrv9002_splitdma.xml
pytest_libiio/resources/devices/adrv9361-z7035.xml
pytest_libiio/resources/devices/adrv9364-z7020.xml
pytest_libiio/resources/devices/adt7420.xml
pytest_libiio/resources/devices/adxl355.xml
pytest_libiio/resources/devices/cn0511.xml
pytest_libiio/resources/devices/cn0540.xml
pytest_libiio/resources/devices/daq2.xml
pytest_libiio/resources/devices/daq3.xml
pytest_libiio/resources/devices/fmcomms11.xml
pytest_libiio/resources/devices/fmcomms2-3.xml
pytest_libiio/resources/devices/fmcomms4.xml
pytest_libiio/resources/devices/fmcomms5.xml
pytest_libiio/resources/devices/ltc2387.xml
pytest_libiio/resources/devices/pluto.xml
pytest_libiio-0.0.27.dist-info/licenses/LICENSE
pytest_libiio-0.0.27.dist-info/METADATA
pytest_libiio-0.0.27.dist-info/WHEEL
pytest_libiio-0.0.27.dist-info/entry_points.txt
pytest_libiio-0.0.27.dist-info/top_level.txt
pytest_libiio-0.0.27.dist-info/RECORD
