Metadata-Version: 2.4
Name: pytest-libiio
Version: 0.0.27
Summary: A pytest plugin for testing libiio based devices
Author-email: Travis Collins <travis.collins@analog.com>
Maintainer-email: Travis Collins <travis.collins@analog.com>
License: BSD-3-Clause
Project-URL: homepage, https://tfcollins.github.io/pytest-libiio/
Project-URL: documentation, https://tfcollins.github.io/pytest-libiio/
Project-URL: repository, https://github.com/tfcollins/pytest-libiio
Keywords: pytest,libiio,adi,testing
Classifier: Intended Audience :: Developers
Classifier: Operating System :: OS Independent
Classifier: Programming Language :: Python :: 3
Classifier: Programming Language :: Python :: 3.9
Classifier: Programming Language :: Python :: 3.10
Classifier: Programming Language :: Python :: 3.11
Classifier: Programming Language :: Python :: 3.12
Classifier: Topic :: Software Development :: Libraries :: Python Modules
Requires-Python: >=3.9
License-File: LICENSE
Requires-Dist: pytest>=3.5.0
Requires-Dist: pylibiio>=0.23.1
Requires-Dist: pyyaml
Requires-Dist: lxml
Requires-Dist: click
Requires-Dist: pytest-xdist
Provides-Extra: ssh
Requires-Dist: paramiko; extra == "ssh"
Dynamic: license-file
